robopianist/__init__.py
robopianist/cli.py
robopianist/py.typed
robopianist/models/__init__.py
robopianist/models/arenas/__init__.py
robopianist/models/arenas/stage.py
robopianist/models/arenas/stage_test.py
robopianist/models/hands/__init__.py
robopianist/models/hands/base.py
robopianist/models/hands/shadow_hand.py
robopianist/models/hands/shadow_hand_constants.py
robopianist/models/hands/shadow_hand_test.py
robopianist/models/hands/third_party/shadow_hand/LICENSE
robopianist/models/hands/third_party/shadow_hand/README.md
robopianist/models/hands/third_party/shadow_hand/left_hand.xml
robopianist/models/hands/third_party/shadow_hand/right_hand.xml
robopianist/models/hands/third_party/shadow_hand/scene_left.xml
robopianist/models/hands/third_party/shadow_hand/scene_right.xml
robopianist/models/hands/third_party/shadow_hand/shadow_hand.png
robopianist/models/hands/third_party/shadow_hand/assets/f_distal_pst.obj
robopianist/models/hands/third_party/shadow_hand/assets/f_knuckle.obj
robopianist/models/hands/third_party/shadow_hand/assets/f_middle.obj
robopianist/models/hands/third_party/shadow_hand/assets/f_proximal.obj
robopianist/models/hands/third_party/shadow_hand/assets/forearm_0.obj
robopianist/models/hands/third_party/shadow_hand/assets/forearm_1.obj
robopianist/models/hands/third_party/shadow_hand/assets/forearm_collision.obj
robopianist/models/hands/third_party/shadow_hand/assets/lf_metacarpal.obj
robopianist/models/hands/third_party/shadow_hand/assets/mounting_plate.obj
robopianist/models/hands/third_party/shadow_hand/assets/palm.obj
robopianist/models/hands/third_party/shadow_hand/assets/th_distal_pst.obj
robopianist/models/hands/third_party/shadow_hand/assets/th_middle.obj
robopianist/models/hands/third_party/shadow_hand/assets/th_proximal.obj
robopianist/models/hands/third_party/shadow_hand/assets/wrist.obj
robopianist/models/piano/__init__.py
robopianist/models/piano/midi_module.py
robopianist/models/piano/piano.py
robopianist-1.0.10.dist-info/LICENSE
robopianist-1.0.10.dist-info/METADATA
robopianist-1.0.10.dist-info/WHEEL
robopianist-1.0.10.dist-info/entry_points.txt
robopianist-1.0.10.dist-info/top_level.txt
robopianist-1.0.10.dist-info/RECORD
