Metadata-Version: 2.1
Name: robopianist
Version: 1.0.10
Summary: A benchmark for high-dimensional robot control
Home-page: https://github.com/google-research/robopianist
Author: Kevin Zakka
Author-email: kevinarmandzakka@gmail.com
Maintainer: Kevin Zakka
Maintainer-email: kevinarmandzakka@gmail.com
License: Apache License 2.0
Keywords: reinforcement-learning mujoco bimanual dexterous-manipulation piano
Classifier: Development Status :: 5 - Production/Stable
Classifier: Intended Audience :: Developers
Classifier: Intended Audience :: Science/Research
Classifier: License :: OSI Approved :: Apache Software License
Classifier: Natural Language :: English
Classifier: Programming Language :: Python :: 3
Classifier: Programming Language :: Python :: 3.8
Classifier: Programming Language :: Python :: 3.9
Classifier: Programming Language :: Python :: 3.10
Classifier: Programming Language :: Python :: 3.11
Classifier: Topic :: Scientific/Engineering :: Artificial Intelligence
Requires-Python: >=3.8
License-File: LICENSE
Requires-Dist: dm-control >=1.0.16
Requires-Dist: dm-env-wrappers >=0.0.11
Requires-Dist: mujoco >=3.1.1
Requires-Dist: mujoco-utils >=0.0.6
Requires-Dist: note-seq >=0.0.5
Requires-Dist: pretty-midi >=0.2.10
Requires-Dist: pyaudio >=0.2.12
Requires-Dist: pyfluidsynth >=1.3.2
Requires-Dist: scikit-learn
Requires-Dist: termcolor
Requires-Dist: tqdm
Provides-Extra: dev
Requires-Dist: black ; extra == 'dev'
Requires-Dist: ruff ; extra == 'dev'
Requires-Dist: mypy ; extra == 'dev'
Requires-Dist: absl-py ; extra == 'dev'
Requires-Dist: pytest-xdist ; extra == 'dev'
Provides-Extra: test
Requires-Dist: absl-py ; extra == 'test'
Requires-Dist: pytest-xdist ; extra == 'test'
